{"cameraMode":{"drawMode":0,"name":"Shaded","section":"Shading Mode"},"sceneLighting":false,"audioPlay":false,"sceneViewState":{"m_AlwaysRefresh":false,"showFog":true,"showSkybox":false,"showFlares":true,"showImageEffects":true,"showParticleSystems":true,"showVisualEffectGraphs":true,"m_FxEnabled":true},"in2DMode":false,"pivot":{"x":432.0,"y":208.90921020507813,"z":0.0},"rotation":{"x":-0.029380684718489648,"y":0.04228385537862778,"z":-0.0012357644736766816,"w":-0.998695969581604},"size":0.3263757824897766,"orthographic":false}